{"meta_data": {"session_number": "66", "run_number": "0", "version": "0.0.3", "game_name": "Poly Rules", "user_name": "colan", "device_id": "id"}, "data": [{"this": "c", "testing": "a", "game_type": "ultim_eyes", "works": "d", "if": "b"}, {"this": "g", "testing": "e", "game_type": "ultim_eyes", "works": "h", "if": 12341234.0}, {"this": "j", "works": true, "game_type": "contour", "hope": "i"}, {"this": "m", "works": false, "game_type": "contour", "hope": "l"}, {"this": "q", "testing": "o", "game_type": "ultim_eyes", "works": "r", "if": "p"}]}